{"games_data": [{"game_time": 312, "config": {"game_role": "instructor", "map_index": 0, "guid": "852aa822-543d-44b9-8c33-03710f243053"}, "chat": [{"id": "navigator", "msg": "hola, empezamos?", "timestamp": 1718702710601, "lang": "es", "cong_cs": [], "det_cs": []}, {"msg": "yes we shall ", "id": "instructor", "timestamp": 1718702866185, "curr_nav_cell": {"r": 2, "c": 23}, "lang": "eng", "cong_cs": [], "det_cs": []}, {"msg": "estoy en el punto de partida", "id": "navigator", "timestamp": 1718702869087, "lang": "es", "cong_cs": [], "det_cs": []}, {"msg": "veo una ramita hacia la izquierda que lleva a una peque\u00f1a isla con una tiger. \u00bfa d\u00f3nde vamos ahora?", "id": "navigator", "timestamp": 1718702869087, "lang": "mix", "cong_cs": [["incong_masc", "tiger"]], "det_cs": [["fem", "tiger"]]}, {"msg": "ok cross to the the place u see the tiger ", "id": "instructor", "timestamp": 1718702961814, "curr_nav_cell": {"r": 2, "c": 23}, "lang": "eng", "cong_cs": [], "det_cs": []}, {"msg": "\u00a1hecho! estoy en la isla con la tiger", "id": "navigator", "timestamp": 1718702964294, "lang": "mix", "cong_cs": [["incong_masc", "tiger"]], "det_cs": [["fem", "tiger"]]}, {"msg": "\u00bfy ahora qu\u00e9?", "id": "navigator", "timestamp": 1718702964294, "lang": "es", "cong_cs": [], "det_cs": []}, {"msg": "that good ", "id": "instructor", "timestamp": 1718702982639, "curr_nav_cell": {"r": 2, "c": 23}, "lang": "eng", "cong_cs": [], "det_cs": []}, {"msg": "\u00a1genial! \u00bfa d\u00f3nde nos dirigimos a continuaci\u00f3n?", "id": "navigator", "timestamp": 1718702984651, "lang": "es", "cong_cs": [], "det_cs": []}, {"msg": "cross to the the place you see the parrot ", "id": "instructor", "timestamp": 1718703008665, "curr_nav_cell": {"r": 2, "c": 23}, "lang": "eng", "cong_cs": [], "det_cs": []}, {"msg": "de acuerdo, estoy en la gran isla con el loro", "id": "navigator", "timestamp": 1718703011065, "lang": "es", "cong_cs": [], "det_cs": []}, {"msg": "\u00bfqu\u00e9 sigue?", "id": "navigator", "timestamp": 1718703011065, "lang": "es", "cong_cs": [], "det_cs": []}, {"msg": "great ", "id": "instructor", "timestamp": 1718703018114, "curr_nav_cell": {"r": 2, "c": 23}, "lang": "eng", "cong_cs": [], "det_cs": []}, {"msg": "\u00a1genial! \u00bfd\u00f3nde deber\u00eda ir a continuaci\u00f3n?", "id": "navigator", "timestamp": 1718703020682, "lang": "es", "cong_cs": [], "det_cs": []}, {"msg": "cross to the frog", "id": "instructor", "timestamp": 1718703035485, "curr_nav_cell": {"r": 2, "c": 23}, "lang": "eng", "cong_cs": [], "det_cs": []}, {"msg": "listo, estoy en la isla con la rana", "id": "navigator", "timestamp": 1718703042604, "lang": "es", "cong_cs": [], "det_cs": []}, {"msg": "\u00bfqu\u00e9 sigue despu\u00e9s?", "id": "navigator", "timestamp": 1718703042604, "lang": "es", "cong_cs": [], "det_cs": []}, {"msg": "good ", "id": "instructor", "timestamp": 1718703048023, "curr_nav_cell": {"r": 2, "c": 23}, "lang": "eng", "cong_cs": [], "det_cs": []}, {"msg": "\u00a1chido! \u00bfy ahora a d\u00f3nde vamos?", "id": "navigator", "timestamp": 1718703049783, "lang": "es", "cong_cs": [], "det_cs": []}, {"msg": "move to the territory with the elephants ", "id": "instructor", "timestamp": 1718703084094, "curr_nav_cell": {"r": 2, "c": 23}, "lang": "eng", "cong_cs": [], "det_cs": []}, {"msg": "estoy en el lugar con el elefante", "id": "navigator", "timestamp": 1718703089098, "lang": "es", "cong_cs": [], "det_cs": []}, {"msg": "\u00bfcu\u00e1l es el pr\u00f3ximo movimiento?", "id": "navigator", "timestamp": 1718703089098, "lang": "es", "cong_cs": [], "det_cs": []}, {"msg": "ok ", "id": "instructor", "timestamp": 1718703095953, "curr_nav_cell": {"r": 2, "c": 23}, "lang": "none", "cong_cs": [], "det_cs": []}, {"msg": "\u00a1ok! \u00bfcu\u00e1l es nuestro pr\u00f3ximo paso?", "id": "navigator", "timestamp": 1718703098348, "lang": "es", "cong_cs": [], "det_cs": []}, {"msg": "move to the giraffe ", "id": "instructor", "timestamp": 1718703109854, "curr_nav_cell": {"r": 2, "c": 23}, "lang": "eng", "cong_cs": [], "det_cs": []}, {"msg": "\u00a1listo! ya estoy con la jirafa", "id": "navigator", "timestamp": 1718703111467, "lang": "es", "cong_cs": [], "det_cs": []}, {"msg": "that good ", "id": "instructor", "timestamp": 1718703118183, "curr_nav_cell": {"r": 2, "c": 23}, "lang": "eng", "cong_cs": [], "det_cs": []}, {"msg": "\u00a1genial! \u00bfcu\u00e1l es nuestra pr\u00f3xima jugada?", "id": "navigator", "timestamp": 1718703119729, "lang": "es", "cong_cs": [], "det_cs": []}, {"msg": "now walk to the treasure chest ", "id": "instructor", "timestamp": 1718703145492, "curr_nav_cell": {"r": 2, "c": 23}, "lang": "eng", "cong_cs": [], "det_cs": []}, {"msg": "he llegado a la treasure", "id": "navigator", "timestamp": 1718703147411, "lang": "mix", "cong_cs": [["incong_masc", "treasure"]], "det_cs": [["fem", "treasure"]]}, {"msg": "*terminado*", "id": "navigator", "timestamp": 1718703147411, "lang": "es", "cong_cs": [], "det_cs": []}], "map_metadata": {"im_width": 2304, "im_height": 1728, "im_src": "map1_1.jpg", "rows": 18, "cols": 24, "end_cell": {"r": 16, "c": 7}, "start_cell": {"r": 2, "c": 23}, "map_idx": 0}, "user_map_path": [{"r": 2, "c": 23}], "cs_metadata": ["veo una ramita hacia la izquierda que lleva a una peque\u00f1a isla con una tiger. \u00bfa d\u00f3nde vamos ahora?", "\u00a1hecho! estoy en la isla con la tiger", "he llegado a la treasure"]}, {"game_time": 420, "config": {"game_role": "navigator", "map_index": 1, "guid": "ccd58cb8-26d2-43bc-be30-6e1dc8908014"}, "chat": [{"id": "instructor", "msg": "hola! que comience el juego!!", "timestamp": 1718703165209, "lang": "es", "cong_cs": [], "det_cs": []}, {"msg": "let begin ", "id": "navigator", "timestamp": 1718703183156, "curr_nav_cell": {"r": 2, "c": 20}, "lang": "eng", "cong_cs": [], "det_cs": []}, {"msg": "\u00a1perfecto! vamos a empezar", "id": "instructor", "timestamp": 1718703188426, "lang": "es", "cong_cs": [], "det_cs": []}, {"msg": "primero, dale un saludo a nuestro amigo el perro blanco. desde donde est\u00e1s, da unos pasos a la izquierda, bajo el banco de madera y cruza el sendero hasta casi llegar al puesto de flores", "id": "instructor", "timestamp": 1718703188426, "lang": "es", "cong_cs": [], "det_cs": []}, {"msg": "hello ", "id": "navigator", "timestamp": 1718703194243, "curr_nav_cell": {"r": 2, "c": 20}, "lang": "eng", "cong_cs": [], "det_cs": []}, {"msg": "\u00a1genial! ahora vamos a girar", "id": "instructor", "timestamp": 1718703197476, "lang": "es", "cong_cs": [], "det_cs": []}, {"msg": "haz un giro completo a la izquierda, vuelve a cruzar el sendero y dir\u00edgete de nuevo hacia el perro blanco", "id": "instructor", "timestamp": 1718703197476, "lang": "es", "cong_cs": [], "det_cs": []}, {"msg": "im at the flower shop ", "id": "navigator", "timestamp": 1718703271717, "curr_nav_cell": {"r": 6, "c": 15}, "lang": "eng", "cong_cs": [], "det_cs": []}, {"msg": "no, no, un peque\u00f1o error", "id": "instructor", "timestamp": 1718703276176, "lang": "es", "cong_cs": [], "det_cs": []}, {"msg": "no necesitas llegar a la tienda de flores. intenta regresar al perro blanco", "id": "instructor", "timestamp": 1718703276176, "lang": "es", "cong_cs": [], "det_cs": []}, {"msg": "ok im at the white dog ", "id": "navigator", "timestamp": 1718703302948, "curr_nav_cell": {"r": 2, "c": 19}, "lang": "eng", "cong_cs": [], "det_cs": []}, {"msg": "bien echo! ahora haz un cruce sur, al otro lado del ramal, y sigue hacia el sur", "id": "instructor", "timestamp": 1718703309553, "lang": "es", "cong_cs": [], "det_cs": []}, {"msg": "ah\u00ed encontrar\u00e1s a otro amigo de color blanco, un perrito junto a un mantel de picnic de cuadros rojos y blancos", "id": "instructor", "timestamp": 1718703309553, "lang": "mix", "cong_cs": [], "det_cs": []}, {"msg": "done ", "id": "navigator", "timestamp": 1718703327079, "curr_nav_cell": {"r": 7, "c": 20}, "lang": "eng", "cong_cs": [], "det_cs": []}, {"msg": "\u00a1perfecto! ahora vamos a mover un poquito m\u00e1s", "id": "instructor", "timestamp": 1718703332623, "lang": "es", "cong_cs": [], "det_cs": []}, {"msg": "done ", "id": "navigator", "timestamp": 1718703340982, "curr_nav_cell": {"r": 11, "c": 20}, "lang": "eng", "cong_cs": [], "det_cs": []}, {"msg": "toma el camino sobre el mat, rozando un bol de frutas rojas, y sigue hacia el oeste", "id": "instructor", "timestamp": 1718703346587, "lang": "mix", "cong_cs": [["incong_fem", "mat"]], "det_cs": [["masc", "mat"]]}, {"msg": "est\u00e1s haciendo un gran trabajo!", "id": "instructor", "timestamp": 1718703346587, "lang": "es", "cong_cs": [], "det_cs": []}, {"msg": "done ", "id": "navigator", "timestamp": 1718703358284, "curr_nav_cell": {"r": 14, "c": 19}, "lang": "eng", "cong_cs": [], "det_cs": []}, {"msg": "bien, ahora veamos qu\u00e9 m\u00e1s tenemos por delante", "id": "instructor", "timestamp": 1718703360454, "lang": "es", "cong_cs": [], "det_cs": []}, {"msg": "a branch ", "id": "navigator", "timestamp": 1718703416766, "curr_nav_cell": {"r": 15, "c": 18}, "lang": "eng", "cong_cs": [], "det_cs": []}, {"msg": "s\u00ed, eso es", "id": "instructor", "timestamp": 1718703423749, "lang": "es", "cong_cs": [], "det_cs": []}, {"msg": "ahora cruza esa rama de madera y contin\u00faa hacia el norte", "id": "instructor", "timestamp": 1718703423749, "lang": "es", "cong_cs": [], "det_cs": []}, {"msg": "done ", "id": "navigator", "timestamp": 1718703440084, "curr_nav_cell": {"r": 10, "c": 12}, "lang": "eng", "cong_cs": [], "det_cs": []}, {"msg": "magn\u00edfico! ahora toca un peque\u00f1o desaf\u00edo de evasi\u00f3n", "id": "instructor", "timestamp": 1718703443776, "lang": "es", "cong_cs": [], "det_cs": []}, {"msg": "what next ", "id": "navigator", "timestamp": 1718703456329, "curr_nav_cell": {"r": 9, "c": 12}, "lang": "eng", "cong_cs": [], "det_cs": []}, {"msg": "ve a la derecha del arbusto verde y camina alrededor sin tocarlo hasta llegar al puesto de flores", "id": "instructor", "timestamp": 1718703459045, "lang": "es", "cong_cs": [], "det_cs": []}, {"msg": "done", "id": "navigator", "timestamp": 1718703480043, "curr_nav_cell": {"r": 6, "c": 13}, "lang": "eng", "cong_cs": [], "det_cs": []}, {"msg": "\u00a1genial! ahora vamos a tomar otro camino", "id": "instructor", "timestamp": 1718703483147, "lang": "es", "cong_cs": [], "det_cs": []}, {"msg": "what path", "id": "navigator", "timestamp": 1718703493608, "curr_nav_cell": {"r": 6, "c": 13}, "lang": "eng", "cong_cs": [], "det_cs": []}, {"msg": "gira a la izquierda, pasa por debajo del puesto de flores y contin\u00faa hasta llegar a un gran puente con dos personas en bicicleta, sigue hacia el oeste", "id": "instructor", "timestamp": 1718703499409, "lang": "es", "cong_cs": [], "det_cs": []}, {"msg": "done ", "id": "navigator", "timestamp": 1718703542198, "curr_nav_cell": {"r": 8, "c": 4}, "lang": "eng", "cong_cs": [], "det_cs": []}, {"msg": "\u00a1muy bien! seguro est\u00e1s apreciando los detalles alrededor", "id": "instructor", "timestamp": 1718703548064, "lang": "es", "cong_cs": [], "det_cs": []}, {"msg": "yes", "id": "navigator", "timestamp": 1718703556042, "curr_nav_cell": {"r": 8, "c": 4}, "lang": "eng", "cong_cs": [], "det_cs": []}, {"msg": "muy bien, una vez que pasaste la bridge, encontrar\u00e1s a dos ancianitos leyendo peri\u00f3dicos en una bench", "id": "instructor", "timestamp": 1718703560246, "lang": "mix", "cong_cs": [["incong_masc", "bridge"], ["incong_masc", "bench"]], "det_cs": [["fem", "bridge"], ["fem", "bench"]]}, {"msg": "pasa entre ellos", "id": "instructor", "timestamp": 1718703560246, "lang": "es", "cong_cs": [], "det_cs": []}, {"msg": "what next", "id": "navigator", "timestamp": 1718703563608, "curr_nav_cell": {"r": 8, "c": 4}, "lang": "eng", "cong_cs": [], "det_cs": []}, {"msg": "ahora, camina un poco hacia el sur, entre los ancianos y otro ramal de madera para alcanzar un arbusto verde que est\u00e1 al final de la rama de madera", "id": "instructor", "timestamp": 1718703570579, "lang": "es", "cong_cs": [], "det_cs": []}, {"msg": "next", "id": "navigator", "timestamp": 1718703585189, "curr_nav_cell": {"r": 16, "c": 10}, "lang": "eng", "cong_cs": [], "det_cs": []}, {"msg": "\u00a1sigamos avanzando! ahora, gira a la derecha y camina entre el ramal y la bush, hacia el este", "id": "instructor", "timestamp": 1718703588089, "lang": "es", "cong_cs": [["incong_masc", "bush"]], "det_cs": [["fem", "bush"]]}], "map_metadata": {"im_width": 2304, "im_height": 1728, "im_src": "map2_0.jpg", "rows": 18, "cols": 24, "end_cell": {"r": 12, "c": 6}, "start_cell": {"r": 2, "c": 20}, "map_idx": 1}, "user_map_path": [{"r": 2, "c": 20}, {"r": 2, "c": 19}, {"r": 2, "c": 18}, {"r": 2, "c": 17}, {"r": 3, "c": 17}, {"r": 3, "c": 16}, {"r": 4, "c": 16}, {"r": 5, "c": 16}, {"r": 5, "c": 15}, {"r": 6, "c": 15}, {"r": 6, "c": 16}, {"r": 5, "c": 16}, {"r": 4, "c": 16}, {"r": 3, "c": 16}, {"r": 2, "c": 16}, {"r": 2, "c": 17}, {"r": 2, "c": 18}, {"r": 2, "c": 19}, {"r": 1, "c": 19}, {"r": 2, "c": 19}, {"r": 3, "c": 19}, {"r": 4, "c": 19}, {"r": 5, "c": 19}, {"r": 5, "c": 20}, {"r": 6, "c": 20}, {"r": 7, "c": 20}, {"r": 8, "c": 20}, {"r": 9, "c": 20}, {"r": 10, "c": 20}, {"r": 11, "c": 20}, {"r": 12, "c": 20}, {"r": 13, "c": 20}, {"r": 13, "c": 19}, {"r": 14, "c": 19}, {"r": 15, "c": 19}, {"r": 15, "c": 18}, {"r": 15, "c": 17}, {"r": 15, "c": 16}, {"r": 15, "c": 15}, {"r": 15, "c": 14}, {"r": 14, "c": 14}, {"r": 13, "c": 14}, {"r": 13, "c": 13}, {"r": 12, "c": 13}, {"r": 11, "c": 13}, {"r": 11, "c": 12}, {"r": 10, "c": 12}, {"r": 9, "c": 12}, {"r": 8, "c": 12}, {"r": 7, "c": 12}, {"r": 6, "c": 12}, {"r": 6, "c": 13}, {"r": 5, "c": 13}, {"r": 5, "c": 12}, {"r": 5, "c": 11}, {"r": 5, "c": 10}, {"r": 6, "c": 10}, {"r": 6, "c": 9}, {"r": 6, "c": 8}, {"r": 6, "c": 7}, {"r": 6, "c": 6}, {"r": 6, "c": 5}, {"r": 7, "c": 5}, {"r": 7, "c": 4}, {"r": 8, "c": 4}, {"r": 9, "c": 4}, {"r": 10, "c": 4}, {"r": 11, "c": 4}, {"r": 12, "c": 4}, {"r": 13, "c": 4}, {"r": 14, "c": 4}, {"r": 15, "c": 4}, {"r": 15, "c": 5}, {"r": 16, "c": 5}, {"r": 16, "c": 6}, {"r": 16, "c": 7}, {"r": 16, "c": 8}, {"r": 16, "c": 9}, {"r": 16, "c": 10}], "cs_metadata": ["muy bien, una vez que pasaste la bridge, encontrar\u00e1s a dos ancianitos leyendo peri\u00f3dicos en una bench", "muy bien, una vez que pasaste la bridge, encontrar\u00e1s a dos ancianitos leyendo peri\u00f3dicos en una bench", "\u00a1sigamos avanzando! ahora, gira a la derecha y camina entre el ramal y la bush, hacia el este"]}, {"game_time": 127, "config": {"game_role": "instructor", "map_index": 2, "guid": "65c2c46b-9b85-4e4e-ad69-b98a25fe1692"}, "chat": [{"id": "navigator", "msg": "hola!!! ya comenzamos?", "timestamp": 1718703595076, "lang": "es", "cong_cs": [], "det_cs": []}, {"msg": "yes", "id": "instructor", "timestamp": 1718703612600, "curr_nav_cell": {"r": 3, "c": 9}, "lang": "eng", "cong_cs": [], "det_cs": []}, {"msg": "\u00a1genial! comenzamos en una tienda en el norte del mapa", "id": "navigator", "timestamp": 1718703615088, "lang": "es", "cong_cs": [], "det_cs": []}, {"msg": "\u00bfhacia d\u00f3nde deber\u00eda ir?", "id": "navigator", "timestamp": 1718703615088, "lang": "es", "cong_cs": [], "det_cs": []}, {"msg": "come to the place u see the dog ", "id": "instructor", "timestamp": 1718703640955, "curr_nav_cell": {"r": 3, "c": 9}, "lang": "eng", "cong_cs": [], "det_cs": []}, {"msg": "de acuerdo, estoy caminando hacia el sur, veo a la dog junto al fuego", "id": "navigator", "timestamp": 1718703643892, "lang": "mix", "cong_cs": [["incong_masc", "dog"]], "det_cs": [["fem", "dog"]]}, {"msg": "\u00bfqu\u00e9 sigue?", "id": "navigator", "timestamp": 1718703643892, "lang": "es", "cong_cs": [], "det_cs": []}, {"msg": "cross the fire and walk to the car ", "id": "instructor", "timestamp": 1718703665588, "curr_nav_cell": {"r": 3, "c": 9}, "lang": "eng", "cong_cs": [], "det_cs": []}, {"msg": "vale, cruc\u00e9 la fire y ahora estoy al lado del auto azul", "id": "navigator", "timestamp": 1718703668490, "lang": "mix", "cong_cs": [["incong_masc", "fire"]], "det_cs": [["fem", "fire"]]}, {"msg": "\u00bfahora qu\u00e9 hago?", "id": "navigator", "timestamp": 1718703668490, "lang": "es", "cong_cs": [], "det_cs": []}, {"msg": "that great ", "id": "instructor", "timestamp": 1718703682653, "curr_nav_cell": {"r": 3, "c": 9}, "lang": "eng", "cong_cs": [], "det_cs": []}, {"msg": "\u00a1gracias! \u00bfpor d\u00f3nde contin\u00fao?", "id": "navigator", "timestamp": 1718703684359, "lang": "es", "cong_cs": [], "det_cs": []}, {"msg": "move closer to the telescope ", "id": "instructor", "timestamp": 1718703697280, "curr_nav_cell": {"r": 3, "c": 9}, "lang": "eng", "cong_cs": [], "det_cs": []}, {"msg": "listo, ahora estoy cerca del telescopio azul", "id": "navigator", "timestamp": 1718703699769, "lang": "es", "cong_cs": [], "det_cs": []}, {"msg": "that great ", "id": "instructor", "timestamp": 1718703715133, "curr_nav_cell": {"r": 3, "c": 9}, "lang": "eng", "cong_cs": [], "det_cs": []}, {"msg": "\u00a1perfecto! \u00bfy ahora qu\u00e9?", "id": "navigator", "timestamp": 1718703716686, "lang": "es", "cong_cs": [], "det_cs": []}, {"msg": "move to the house ", "id": "instructor", "timestamp": 1718703723214, "curr_nav_cell": {"r": 3, "c": 9}, "lang": "eng", "cong_cs": [], "det_cs": []}, {"msg": "\u00a1hecho! ya llegu\u00e9 a la casa de madera rodeada de rocas", "id": "navigator", "timestamp": 1718703725537, "lang": "es", "cong_cs": [], "det_cs": []}, {"msg": "*terminado*", "id": "navigator", "timestamp": 1718703725537, "lang": "es", "cong_cs": [], "det_cs": []}], "map_metadata": {"im_width": 2304, "im_height": 1728, "im_src": "map3_1.jpg", "rows": 18, "cols": 24, "end_cell": {"r": 13, "c": 9}, "start_cell": {"r": 3, "c": 9}, "map_idx": 2}, "user_map_path": [{"r": 3, "c": 9}], "cs_metadata": ["de acuerdo, estoy caminando hacia el sur, veo a la dog junto al fuego", "vale, cruc\u00e9 la fire y ahora estoy al lado del auto azul"]}, {"game_time": 420, "config": {"game_role": "navigator", "map_index": 3, "guid": "3d94feab-f98f-4c3c-937d-40470eaa9752"}, "chat": [{"id": "instructor", "msg": "hola, q tal? empezamos el juego?", "timestamp": 1718703729899, "lang": "es", "cong_cs": [], "det_cs": []}, {"msg": "ok", "id": "navigator", "timestamp": 1718703741211, "curr_nav_cell": {"r": 3, "c": 23}, "lang": "none", "cong_cs": [], "det_cs": []}, {"msg": "genial, ahora est\u00e1s cerca de tres palmeras", "id": "instructor", "timestamp": 1718703743932, "lang": "es", "cong_cs": [], "det_cs": []}, {"msg": "deber\u00edas comenzar avanzando hacia el sudoeste, justo debajo de la primera palmera", "id": "instructor", "timestamp": 1718703743932, "lang": "es", "cong_cs": [], "det_cs": []}, {"msg": "done", "id": "navigator", "timestamp": 1718703778102, "curr_nav_cell": {"r": 5, "c": 21}, "lang": "eng", "cong_cs": [], "det_cs": []}, {"msg": "ahora, gira a la derecha y ve hacia la segunda palmera", "id": "instructor", "timestamp": 1718703780050, "lang": "es", "cong_cs": [], "det_cs": []}, {"msg": "done ", "id": "navigator", "timestamp": 1718703788978, "curr_nav_cell": {"r": 5, "c": 20}, "lang": "eng", "cong_cs": [], "det_cs": []}, {"msg": "perfecto, ahora gira bruscamente a la izquierda antes de la tercera palmera y sigue hacia el sur", "id": "instructor", "timestamp": 1718703793467, "lang": "es", "cong_cs": [], "det_cs": []}, {"msg": "done ", "id": "navigator", "timestamp": 1718703828646, "curr_nav_cell": {"r": 6, "c": 20}, "lang": "eng", "cong_cs": [], "det_cs": []}, {"msg": "muy bien, ahora ve m\u00e1s al sur pero movi\u00e9ndote siempre a la izquierda de ese cachorrito marr\u00f3n", "id": "instructor", "timestamp": 1718703838861, "lang": "es", "cong_cs": [], "det_cs": []}, {"msg": "luego gira a la derecha, todav\u00eda hacia el sur", "id": "instructor", "timestamp": 1718703838861, "lang": "es", "cong_cs": [], "det_cs": []}, {"msg": "done ", "id": "navigator", "timestamp": 1718703859311, "curr_nav_cell": {"r": 7, "c": 23}, "lang": "eng", "cong_cs": [], "det_cs": []}, {"msg": "perfecto, ahora debes cruzar entre la roca grande a tu izquierda y la peque\u00f1a a tu derecha", "id": "instructor", "timestamp": 1718703862824, "lang": "es", "cong_cs": [], "det_cs": []}, {"msg": "te encontrar\u00e1s con la ocean", "id": "instructor", "timestamp": 1718703862824, "lang": "mix", "cong_cs": [["incong_masc", "ocean"]], "det_cs": [["fem", "ocean"]]}, {"msg": "done ", "id": "navigator", "timestamp": 1718703905595, "curr_nav_cell": {"r": 14, "c": 14}, "lang": "eng", "cong_cs": [], "det_cs": []}, {"msg": "genial, ahora entra al agua y encontrar\u00e1s un gran cangrejo rojo", "id": "instructor", "timestamp": 1718703907977, "lang": "es", "cong_cs": [], "det_cs": []}, {"msg": "done ", "id": "navigator", "timestamp": 1718703927640, "curr_nav_cell": {"r": 16, "c": 20}, "lang": "eng", "cong_cs": [], "det_cs": []}, {"msg": "\u00a1bien hecho! ahora gira a la derecha, o sea al oeste, y sigue a lo largo de la gran roca", "id": "instructor", "timestamp": 1718703932041, "lang": "es", "cong_cs": [], "det_cs": []}, {"msg": "contin\u00faa hacia el oeste en el agua", "id": "instructor", "timestamp": 1718703932041, "lang": "es", "cong_cs": [], "det_cs": []}, {"msg": "done", "id": "navigator", "timestamp": 1718703966347, "curr_nav_cell": {"r": 15, "c": 20}, "lang": "eng", "cong_cs": [], "det_cs": []}, {"msg": "muy bien, despu\u00e9s de pasar una tercera roca, de tama\u00f1o medio, ver\u00e1s una shark", "id": "instructor", "timestamp": 1718703970658, "lang": "mix", "cong_cs": [["incong_masc", "shark"]], "det_cs": [["fem", "shark"]]}, {"msg": "cuando llegues all\u00ed, gira bruscamente a la derecha", "id": "instructor", "timestamp": 1718703970658, "lang": "es", "cong_cs": [], "det_cs": []}, {"msg": "done", "id": "navigator", "timestamp": 1718703998788, "curr_nav_cell": {"r": 12, "c": 12}, "lang": "eng", "cong_cs": [], "det_cs": []}, {"msg": "\u00a1perfecto! ahora, debes volver a tierra firme, cruzar entre la roca mediana y una pelota tricolor: azul, amarilla y blanca", "id": "instructor", "timestamp": 1718704003723, "lang": "es", "cong_cs": [], "det_cs": []}, {"msg": "sigue hacia el norte", "id": "instructor", "timestamp": 1718704003723, "lang": "es", "cong_cs": [], "det_cs": []}, {"msg": "done", "id": "navigator", "timestamp": 1718704018653, "curr_nav_cell": {"r": 15, "c": 8}, "lang": "eng", "cong_cs": [], "det_cs": []}, {"msg": "genial, va muy bien", "id": "instructor", "timestamp": 1718704022755, "lang": "es", "cong_cs": [], "det_cs": []}, {"msg": "ahora dir\u00edgete un poco hacia la izquierda, al noroeste, y cruza entre una carpa roja en tu izquierda y un altavoz grande a tu derecha", "id": "instructor", "timestamp": 1718704022755, "lang": "es", "cong_cs": [], "det_cs": []}, {"msg": "done", "id": "navigator", "timestamp": 1718704043454, "curr_nav_cell": {"r": 4, "c": 9}, "lang": "eng", "cong_cs": [], "det_cs": []}, {"msg": "\u00a1vas genial! ahora, ve en un arco alrededor de la tienda y luego sigue hacia el sur hacia la sea", "id": "instructor", "timestamp": 1718704050215, "lang": "es", "cong_cs": [["incong_masc", "sea"]], "det_cs": [["fem", "sea"]]}, {"msg": "pero ten en cuenta, no llegues al agua", "id": "instructor", "timestamp": 1718704050215, "lang": "es", "cong_cs": [], "det_cs": []}, {"msg": "done", "id": "navigator", "timestamp": 1718704065276, "curr_nav_cell": {"r": 5, "c": 9}, "lang": "eng", "cong_cs": [], "det_cs": []}, {"msg": "\u00a1perfecto! ahora gira a la derecha, o sea, al oeste, y avanza debajo de un kayak rojo", "id": "instructor", "timestamp": 1718704068455, "lang": "mix", "cong_cs": [], "det_cs": []}, {"msg": "done", "id": "navigator", "timestamp": 1718704096180, "curr_nav_cell": {"r": 12, "c": 4}, "lang": "eng", "cong_cs": [], "det_cs": []}, {"msg": "muy bien, ahora gira a la derecha 90 grados, o sea, al norte, sigue a lo largo del kayak y llegar\u00e1s a un peque\u00f1o arbusto verde", "id": "instructor", "timestamp": 1718704100723, "lang": "mix", "cong_cs": [], "det_cs": []}, {"msg": "done", "id": "navigator", "timestamp": 1718704125184, "curr_nav_cell": {"r": 3, "c": 0}, "lang": "eng", "cong_cs": [], "det_cs": []}, {"msg": "\u00a1fant\u00e1stico! lograste completar el camino", "id": "instructor", "timestamp": 1718704129684, "lang": "es", "cong_cs": [], "det_cs": []}, {"msg": "muy buen trabajo, camarada. \u00bfte ha gustado el juego?", "id": "instructor", "timestamp": 1718704129684, "lang": "es", "cong_cs": [], "det_cs": []}, {"msg": "yes", "id": "navigator", "timestamp": 1718704145031, "curr_nav_cell": {"r": 3, "c": 0}, "lang": "eng", "cong_cs": [], "det_cs": []}, {"msg": "genial, me alegra que hayas disfrutado", "id": "instructor", "timestamp": 1718704148067, "lang": "es", "cong_cs": [], "det_cs": []}, {"msg": "\u00bflisto para otra ronda o es suficiente por hoy?", "id": "instructor", "timestamp": 1718704148067, "lang": "es", "cong_cs": [], "det_cs": []}], "map_metadata": {"im_width": 2304, "im_height": 1728, "im_src": "map4_0.jpg", "rows": 18, "cols": 24, "end_cell": {"r": 7, "c": 0}, "start_cell": {"r": 3, "c": 23}, "map_idx": 3}, "user_map_path": [{"r": 3, "c": 23}, {"r": 3, "c": 22}, {"r": 3, "c": 21}, {"r": 4, "c": 21}, {"r": 5, "c": 21}, {"r": 5, "c": 20}, {"r": 6, "c": 20}, {"r": 7, "c": 20}, {"r": 7, "c": 21}, {"r": 7, "c": 22}, {"r": 7, "c": 23}, {"r": 8, "c": 23}, {"r": 9, "c": 23}, {"r": 9, "c": 22}, {"r": 9, "c": 21}, {"r": 9, "c": 20}, {"r": 9, "c": 19}, {"r": 9, "c": 18}, {"r": 9, "c": 17}, {"r": 9, "c": 16}, {"r": 10, "c": 16}, {"r": 11, "c": 16}, {"r": 12, "c": 16}, {"r": 12, "c": 15}, {"r": 12, "c": 14}, {"r": 13, "c": 14}, {"r": 14, "c": 14}, {"r": 15, "c": 14}, {"r": 15, "c": 15}, {"r": 15, "c": 16}, {"r": 16, "c": 16}, {"r": 16, "c": 17}, {"r": 16, "c": 18}, {"r": 16, "c": 19}, {"r": 16, "c": 20}, {"r": 15, "c": 20}, {"r": 14, "c": 20}, {"r": 13, "c": 20}, {"r": 12, "c": 20}, {"r": 11, "c": 20}, {"r": 10, "c": 20}, {"r": 10, "c": 19}, {"r": 10, "c": 18}, {"r": 10, "c": 17}, {"r": 10, "c": 16}, {"r": 10, "c": 15}, {"r": 10, "c": 14}, {"r": 10, "c": 13}, {"r": 10, "c": 12}, {"r": 11, "c": 12}, {"r": 12, "c": 12}, {"r": 12, "c": 11}, {"r": 12, "c": 10}, {"r": 13, "c": 10}, {"r": 14, "c": 10}, {"r": 14, "c": 9}, {"r": 15, "c": 9}, {"r": 15, "c": 8}, {"r": 15, "c": 7}, {"r": 15, "c": 6}, {"r": 14, "c": 6}, {"r": 13, "c": 6}, {"r": 12, "c": 6}, {"r": 11, "c": 6}, {"r": 10, "c": 6}, {"r": 9, "c": 6}, {"r": 8, "c": 6}, {"r": 7, "c": 6}, {"r": 6, "c": 6}, {"r": 5, "c": 6}, {"r": 4, "c": 6}, {"r": 4, "c": 7}, {"r": 4, "c": 8}, {"r": 4, "c": 9}, {"r": 5, "c": 9}, {"r": 6, "c": 9}, {"r": 7, "c": 9}, {"r": 8, "c": 9}, {"r": 9, "c": 9}, {"r": 10, "c": 9}, {"r": 11, "c": 9}, {"r": 12, "c": 9}, {"r": 12, "c": 8}, {"r": 12, "c": 7}, {"r": 12, "c": 6}, {"r": 12, "c": 5}, {"r": 12, "c": 4}, {"r": 12, "c": 3}, {"r": 12, "c": 2}, {"r": 11, "c": 2}, {"r": 10, "c": 2}, {"r": 9, "c": 2}, {"r": 8, "c": 2}, {"r": 7, "c": 2}, {"r": 6, "c": 2}, {"r": 5, "c": 2}, {"r": 4, "c": 2}, {"r": 4, "c": 1}, {"r": 4, "c": 0}, {"r": 3, "c": 0}], "cs_metadata": ["te encontrar\u00e1s con la ocean", "muy bien, despu\u00e9s de pasar una tercera roca, de tama\u00f1o medio, ver\u00e1s una shark", "\u00a1vas genial! ahora, ve en un arco alrededor de la tienda y luego sigue hacia el sur hacia la sea"]}], "general_survey": [{"answer": "64", "question": "Age:"}, {"answer": "male", "question": "Gender:"}, {"answer": "nigeria abuja ", "question": "Place of birth (state, country):"}, {"answer": "united states of America ", "question": "Place of current residence (approximate city, state, country):"}, {"answer": "some graduate school", "question": "Highest level of education received:"}, {"answer": "english", "question": "Native language(s):"}, {"answer": "Spanish ", "question": "Do you speak any other languages?"}, {"answer": "english", "question": "What languages are currently spoken in your home?"}, {"answer": "yes ", "question": "Have you spent extended time (e.g., more than 6 months) living in another country?"}, {"answer": "english ", "question": "Enter your native language, or the language you are providing answers for, here:"}, {"answer": 85, "question": "How would you rate your fluency in your native language, for each of these categories: Reading"}, {"answer": 80, "question": "How would you rate your fluency in your native language, for each of these categories: Writing"}, {"answer": 92, "question": "How would you rate your fluency in your native language, for each of these categories: Speaking"}, {"answer": 87, "question": "How would you rate your fluency in your native language, for each of these categories: Listening"}, {"answer": 81, "question": "Please rate how likely you are to use your native language in the following contexts: At work"}, {"answer": 74, "question": "Please rate how likely you are to use your native language in the following contexts: At home"}, {"answer": 78, "question": "Please rate how likely you are to use your native language in the following contexts: Interacting with friends"}, {"answer": 79, "question": "Please rate how likely you are to use your native language in the following contexts: Interacting with family"}, {"answer": 88, "question": "Please rate how likely you are to use your native language in the following contexts: Entertainment (TV series, music, etc.)"}, {"answer": "spanish", "question": "Enter your most proficient second language here:"}, {"answer": 50, "question": "How would you rate your fluency in your second language, for each of these categories: Reading"}, {"answer": 50, "question": "How would you rate your fluency in your second language, for each of these categories: Writing"}, {"answer": 50, "question": "How would you rate your fluency in your second language, for each of these categories: Speaking"}, {"answer": 50, "question": "How would you rate your fluency in your second language, for each of these categories: Listening"}, {"answer": "21", "question": "Approximately what age did you begin learning your second language?"}, {"answer": 50, "question": "Please rate how likely you are to use your second language in the following contexts: At work"}, {"answer": 50, "question": "Please rate how likely you are to use your second language in the following contexts: At home"}, {"answer": 50, "question": "Please rate how likely you are to use your second language in the following contexts: Interacting with friends"}, {"answer": 50, "question": "Please rate how likely you are to use your second language in the following contexts: Interacting with family"}, {"answer": 50, "question": "Please rate how likely you are to use your second language in the following contexts: Entertainment (TV series, music, etc.)"}, {"answer": "Valencia for vacation for a year plus ", "question": "Have you ever lived in a home environment or country where your second language was spoken? If so, please explain briefly:"}, {"answer": "no", "question": "Do you speak any additional languages? If so, please describe briefly here."}, {"answer": 59, "question": "On a day-to-day basis, how likely are you to have a conversation using both English and Spanish?"}, {"answer": 35, "question": "How likely would you be to mix languages in the following contexts? At work"}, {"answer": 61, "question": "How likely would you be to mix languages in the following contexts? At home"}, {"answer": 50, "question": "How likely would you be to mix languages in the following contexts? Interacting with friends"}, {"answer": 64, "question": "How likely would you be to mix languages in the following contexts? Interacting with family"}, {"answer": 69, "question": "How likely would you be to mix languages in the following contexts? Using social media"}, {"answer": 62, "question": "When you switch languages, how often is it for the following reasons? To accommodate people who don't share the same language or language fluency."}, {"answer": 50, "question": "When you switch languages, how often is it for the following reasons? For social reasons; one language feels more appropriate."}, {"answer": 50, "question": "When you switch languages, how often is it for the following reasons? I can't think of a word in the current language."}, {"answer": 50, "question": "When you switch languages, how often is it for the following reasons? The word in the other language just fits better."}, {"answer": 50, "question": "When you switch languages, how often is it for the following reasons? It's an accident, or I don't realize I'm doing it."}, {"answer": 50, "question": "When you switch languages, how often is it for the following reasons? I'm more comfortable discussing the topic in the other language."}, {"answer": 50, "question": "Do you enjoy mixing languages in conversation?"}, {"answer": 54, "question": "When you hear others mixing languages in conversation, how do you feel about it?"}, {"answer": 50, "question": "How natural was your conversational partner\u2019s language switching?"}, {"answer": "it was god ", "question": "Any final comments about your partner\u2019s language switching?"}, {"answer": "very interesting survey", "question": "Any final comments about your language background?"}], "map_survey": [{"answer": 65, "question": "How much did you enjoy the task?"}, {"answer": 21, "question": "How difficult was it to communicate with your partner?"}, {"answer": 64, "question": "How successful do you think you were at completing the task?"}, {"answer": 26, "question": "How difficult was it to understand your partner's instructions?"}, {"answer": 68, "question": "How likely is your partner to be a fluent speaker of English?"}, {"answer": 50, "question": "How likely is your partner to be a fluent speaker of Spanish?"}, {"answer": 50, "question": "How likely do you think it is that your partner is bilingual?"}, {"answer": 62, "question": "Please rate your partner according to the following attributes: friendly"}, {"answer": 79, "question": "Please rate your partner according to the following attributes: smart"}, {"answer": 73, "question": "Please rate your partner according to the following attributes: collaborative"}, {"answer": 64, "question": "Please rate your partner according to the following attributes: honest"}, {"answer": 65, "question": "Please rate your partner according to the following attributes: funny"}, {"answer": 74, "question": "How likely do you think it was that you were talking to a chatbot rather than a human?"}, {"answer": 77, "question": "If you were communicating with a chat bot, would you want them to communicate in both English and Spanish?"}], "clinet_version": "2.4.0_p", "prolific": {"prolific_id": "66407b9a5c59851691b68829", "study_id": "667065914d1ee891659ac114", "seassion_id": "667151ffd83e94ce9278ddae"}, "server_version": "2.4.1_p", "cs_strategy": "insertional_spanish_incongruent1"}